[
    {
      "id": 3,
      "question": "Тъмна или светла коса",
      "answers": {
        "Светла": ["math", "chem"],
        "Тъмна": []
      }
    },
    {
      "id": 8,
      "question": "Плосък или изпъкнал тил",
      "answers": {
        "Плосък": ["math"],
        "Изпъкнал": []
      }
    },
    {
      "id": 9,
      "question": "Трапчинка на тила",
      "answers": {
        "Има": [],
        "Няма": ["chem", "geo"]
      }
    },
    {
      "id": 14,
      "question": "Право или скосено слепоочие",
      "answers": {
        "Право": ["med"],
        "Скосено": []
      }
    },
    {
      "id": 20,
      "question": "Червендалесто или млечно лице",
      "answers": {
        "Червендалесто": [],
        "Млечно": ["art"]
      }
    },
    {
      "id": 33,
      "question": "Гладки или издадени скули",
      "answers": {
        "Гладки": ["math"],
        "Издадени": []
      },
      "img_a": "../img/33_a",
      "img_b": "../img/33_b"
    },
    {
      "id": 34,
      "question": "Тъп или прав ъгъл на челюстта",
      "answers": {
        "Тъп": [],
        "Прав": [],
        "img_a": "../img/34_a",
        "img_b": "../img/34_b"
      }
    },
    {
      "id": 36,
      "question": "Изпъкнало или гладко надвеждие",
      "answers": {
        "Изпъкнало": ["journal"],
        "Гладко": [],
        "img_a": "../img/36_a",
        "img_b": "../img/36_b"
      }
    },
    {
      "id": 38,
      "question": "Прави или дъгообразни вежди",
      "answers": {
        "Прави": ["chem", "geo"],
        "Дъгообразни": [],
        "img_a": "../img/38_a",
        "img_b": "../img/38_b"
      }
    },
    {
      "id": 44,
      "question": "Широки или тесни вежди",
      "answers": {
        "Широки": ["bio"],
        "Тесни": [],
        "img_a": "../img/44_a",
        "img_b": "../img/44_b"
      }
    },
    {
      "id": 56,
      "question": "Тънки или дебели мигли",
      "answers": {
        "Тънки": [],
        "Дебели": ["bio", "geo", "med"]
      }
    },
    {
      "id": 58,
      "question": "Прикрита или виждаща се гънка на горния клепач",
      "answers": {
        "Прикрита": ["geo", "ped", "art"],
        "Виждаща се": ["math"],
        "img_a": "../img/58_a",
        "img_b": "../img/58_b"
      }
    },
    {
      "id": 62,
      "question": "Висока или ниска основа на носа",
      "answers": {
        "Висока": ["math", "journal"],
        "Ниска": [],
        "img_a": "../img/62_a",
        "img_b": "../img/62_b"
      }
    },
    {
      "id": 64,
      "question": "Основа на носа - с или без вдлъбнатина",
      "answers": {
        "С вдлъбнатина": ["geo"],
        "Без вдлъбнатина": [],
        "img_a": "../img/64_a",
        "img_b": "../img/64_b"
      }
    },
    {
      "id": 66,
      "question": "Липсващ или изразен ъгъл между челото и носа",
      "answers": {
        "Липсващ": ["chem", "history"],
        "Изразен": [],
        "img_a": "../img/66_a",
        "img_b": "../img/66_b"
      }
    },
    {
      "id": 77,
      "question": "С или без извивка на гърбицата на носа",
      "answers": {
        "С извивка": [],
        "Без извивка": ["bio", "geo"],
        "img_a": "../img/77_a",
        "img_b": "../img/77_b"
      }
    },
    {
      "id": 80,
      "question": "Гънки на страните на носа",
      "answers": {
        "Има": [],
        "Няма": [],
        "img_a": "../img/80_a",
        "img_b": "../img/80_b"
      }
    },
    {
      "id": 90,
      "question": "Филтър",
      "answers": {
        "Правоъгълен": [],
        "Триъгълен": ["ped"]
      }
    },
    {
      "id": 91,
      "question": "Дълбок или изгладен филтър",
      "answers": {
        "Дълбок": ["math"],
        "Изгладен": ["ped"],
        "img_a": "../img/91_a",
        "img_b": "../img/91_b"
      }
    },
    {
      "id": 98,
      "question": "Излизащи напред или вмъкнати устни",
      "answers": {
        "Излизащи напред": [],
        "Вмъкнати": ["bio", "geo", "history"],
        "img_a": "../img/98_a",
        "img_b": "../img/98_b"
      }
    },
    {
      "id": 100,
      "question": "Наклонени или вертикални горни зъби",
      "answers": {
        "Наклонени": [],
        "Вертикални": ["math"],
        "img_a": "../img/100_a",
        "img_b": "../img/100_b"
      }
    },
    {
      "id": 102,
      "question": "Големи или неизпъкващи горни вътрешни резци",
      "answers": {
        "Големи": [],
        "Неизпъкващи": ["ped", "history", "med", "art"],
        "img_a": "../img/102_a",
        "img_b": "../img/102_b"
      }
    },
    {
      "id": 103,
      "question": "Цепнатина между горните резци",
      "answers": {
        "Има": ["math", "journal"],
        "Няма": [],
        "img_a": "../img/103_a",
        "img_b": "../img/103_b"
      }
    },
    {
      "id": 109,
      "question": "Хоризонтална бръчка на брадата",
      "answers": {
        "Има": ["history", "med"],
        "Няма": []
      }
    },
    {
      "id": 113,
      "question": "Единична или двойна брадичка",
      "answers": {
        "Единична": ["chem"],
        "Двойна": [],
        "img_a": "../img/113_a",
        "img_b": "../img/113_b"
      }
    },
    {
      "id": 115,
      "question": "Изпъкнала или незабележима адамова ябълка",
      "answers": {
        "Изпъкнала": [],
        "Незабележима": ["jounal", "math", "art"],
        "img_a": "../img/115_a",
        "img_b": "../img/115_b"
      }
    },
    {
      "id": 117,
      "question": "Щръкнали или прилепнали уши",
      "answers": {
        "Щръкнали": [],
        "Прилепнали": [],
        "img_a": "../img/117_a",
        "img_b": "../img/117_b"
      }
    },
    {
      "id": 121,
      "question": "Ъгловати или закръглени уши",
      "answers": {
        "Ъгловати": ["math"],
        "Закръглени": [],
        "img_a": "../img/121_a",
        "img_b": "../img/121_b"
      }
    },
    {
      "id": 125,
      "question": "Триъгълна или нормална долна мека част на ухото",
      "answers": {
        "Триъгълна": ["chem"],
        "Нормална": ["bio", "geo"],
        "img_a": "../img/125_a",
        "img_b": "../img/125_b"
      }
    },
    {
      "id": 129,
      "question": "Изпъкнала или вдлъбната долна мека част на ухото",
      "answers": {
        "Изпъкнала": [],
        "Вдлъбната": [],
        "img_a": "../img/129_a",
        "img_b": "../img/129_b"
      }
    },
    {
      "id": 134,
      "question": "Малка издутина по ръба на ухото",
      "answers": {
        "Има": [],
        "Няма": ["journal", "history", "ped", "med"],
        "img_a": "../img/134_a",
        "img_b": "../img/134_b"
      }
    },
    {
      "id": 137,
      "question": "Широки или тесни китки",
      "answers": {
        "Широки": ["math"],
        "Тесни": []
      }
    },
    {
      "id": 138,
      "question": "Дълги или къси китки",
      "answers": {
        "Дълги": [],
        "Къси": ["art"]
      }
    },
    {
      "id": 139,
      "question": "Външни вени на китките - релефни или изгладени",
      "answers": {
        "Релефни": [],
        "Изгладени": ["geo", "history", "ped"]
      }
    },
    {
      "id": 141,
      "question": "Груба или гладка кожа по дланта",
      "answers": {
        "груба": [],
        "гладка": ["art"]
      }
    },
    {
      "id": 144,
      "question": "Дланта е слабо или силно изпъстрена с рисунки",
      "answers": {
        "Слабо": ["math"],
        "Силно": []
      }
    },
    {
      "id": 147,
      "question": "Фаланга на големия пръст",
      "answers": {
        "Дълга": [],
        "Къса": ["ped"]
      }
    },
    {
      "id": 148,
      "question": "Талия на големия пръст",
      "answers": {
        "Има": [],
        "Няма": [],
        "img_a": "../img/148_a",
        "img_b": "../img/148_b"
      }
    },
    {
      "id": 150,
      "question": "Къси или дълги нокти",
      "answers": {
        "Къси": ["chem", "geo", "bio"],
        "Дълги": [],
        "img_a": "../img/150_a",
        "img_b": "../img/150_b"
      }
    },
    {
      "id": 153,
      "question": "Гънка на палеца",
      "answers": {
        "Дълга": ["geo", "bio"],
        "Къса": []
      }
    },
    {
      "id": 168,
      "question": "Широки или тесни глезени",
      "answers": {
        "Широки": [],
        "Тесни": ["chem"],
        "img_a": "../img/168_a",
        "img_b": "../img/168_b"
      }
    },
    {
      "id": 170,
      "question": "Хоризонтални или полегати рамене",
      "answers": {
        "Хоризонтални": [],
        "Полегати": ["journal", "journal", "ped", "art"]
      }
    },
    {
      "id": 172,
      "question": "Тесен или широк таз",
      "answers": {
        "Тесен": ["bio", "geo"],
        "Широк": ["art"]
      }
    }
]